<?xml version="1.0" encoding="UTF-8" ?>
<!DOCTYPE mapper PUBLIC "-//mybatis.org//DTD Mapper 3.0//EN" "http://mybatis.org/dtd/mybatis-3-mapper.dtd" >
<mapper namespace="com.ted.resonance.mapper.DataDictBeanMapper" >
  <resultMap id="BaseResultMap" type="com.ted.resonance.entity.DataDictBean" >
    <!--
      WARNING - @mbggenerated
      This element is automatically generated by MyBatis Generator, do not modify.
    -->
    <result column="id" property="id" jdbcType="INTEGER" />
    <result column="category" property="category" jdbcType="BIT" />
    <result column="type" property="type" jdbcType="BIT" />
    <result column="key" property="key" jdbcType="VARCHAR" />
    <result column="value" property="value" jdbcType="VARCHAR" />
    <result column="enabled" property="enabled" jdbcType="CHAR" />
  </resultMap>

  <sql id="Base_Column_List">
        id,category,`type`, `key`, `value`,enabled
  </sql>

  <insert id="insert" parameterType="com.ted.resonance.entity.DataDictBean" >
    <!--
      WARNING - @mbggenerated
      This element is automatically generated by MyBatis Generator, do not modify.
    -->
    insert into exchange.data_dict (id, category, type, key,
      value, enabled)
    values (#{id,jdbcType=INTEGER}, #{category,jdbcType=BIT}, #{type,jdbcType=BIT}, #{key,jdbcType=VARCHAR}, 
      #{value,jdbcType=VARCHAR}, #{enabled,jdbcType=CHAR})
  </insert>
  <insert id="insertSelective" parameterType="com.ted.resonance.entity.DataDictBean" >
    <!--
      WARNING - @mbggenerated
      This element is automatically generated by MyBatis Generator, do not modify.
    -->
    insert into exchange.data_dict
    <trim prefix="(" suffix=")" suffixOverrides="," >
      <if test="id != null" >
        id,
      </if>
      <if test="category != null" >
        category,
      </if>
      <if test="type != null" >
        type,
      </if>
      <if test="key != null" >
        key,
      </if>
      <if test="value != null" >
        value,
      </if>
      <if test="enabled != null" >
        enabled,
      </if>
    </trim>
    <trim prefix="values (" suffix=")" suffixOverrides="," >
      <if test="id != null" >
        #{id,jdbcType=INTEGER},
      </if>
      <if test="category != null" >
        #{category,jdbcType=BIT},
      </if>
      <if test="type != null" >
        #{type,jdbcType=BIT},
      </if>
      <if test="key != null" >
        #{key,jdbcType=VARCHAR},
      </if>
      <if test="value != null" >
        #{value,jdbcType=VARCHAR},
      </if>
      <if test="enabled != null" >
        #{enabled,jdbcType=CHAR},
      </if>
    </trim>
  </insert>


  <select id="queryByKey" resultMap="BaseResultMap" >
    select
    <include refid="Base_Column_List"/>
    from exchange.data_dict
    where `key`= #{key,jdbcType=VARCHAR}
    and enabled ='1' limit 1
  </select>

  <select id="queryAllDict" resultMap="BaseResultMap" >
    select
    <include refid="Base_Column_List"/>
    from exchange.data_dict
    where enabled =1
  </select>




</mapper>